scpfetch/__init__.py
scpfetch/scpfetch.py
scpfetch-0.1.3.dist-info/LICENSE
scpfetch-0.1.3.dist-info/METADATA
scpfetch-0.1.3.dist-info/WHEEL
scpfetch-0.1.3.dist-info/top_level.txt
scpfetch-0.1.3.dist-info/RECORD
