Metadata-Version: 2.1
Name: scpfetch
Version: 0.1.3
Summary: API wrapper for getting SCP data
Home-page: https://github.com/Kanata-05/SCP-API
Author: kanata
Classifier: Programming Language :: Python :: 3
Classifier: License :: OSI Approved :: MIT License
Requires-Python: >=3.7
License-File: LICENSE
Requires-Dist: requests
